moam/__init__.py
moam/jerry/__init__.py
moam/tom/__init__.py
moam/tracer/__init__.py
moam-0.1.1.dist-info/licenses/LICENSE
moam-0.1.1.dist-info/METADATA
moam-0.1.1.dist-info/WHEEL
moam-0.1.1.dist-info/top_level.txt
moam-0.1.1.dist-info/RECORD
